airtunnel/__init__.py
airtunnel/data_asset.py
airtunnel/data_store.py
airtunnel/declaration_store.py
airtunnel/paths.py
airtunnel/metadata/__init__.py
airtunnel/metadata/adapter.py
airtunnel/metadata/entities.py
airtunnel/operators/__init__.py
airtunnel/operators/archival.py
airtunnel/operators/ingestion.py
airtunnel/operators/loading.py
airtunnel/operators/transformation.py
airtunnel/operators/sql/__init__.py
airtunnel/operators/sql/sql_helpers.py
airtunnel/operators/sql/sqloperator.py
airtunnel/sensors/__init__.py
airtunnel/sensors/ingestion.py
airtunnel/sensors/metadata.py
airtunnel-1.0.1.dist-info/LICENSE
airtunnel-1.0.1.dist-info/WHEEL
airtunnel-1.0.1.dist-info/METADATA
airtunnel-1.0.1.dist-info/RECORD
