Metadata-Version: 2.1
Name: airtunnel
Version: 1.0.1
Summary: airtunnel – tame your Airflow!
Home-page: https://github.com/joerg-schneider/airtunnel
License: UNKNOWN
Author: Jörg Schneider
Author-email: joerg@joerg-schneider.org
Requires-Python: >=3.6
Requires-Dist: pandas >= 0.23
Requires-Dist: schema >= 0.6
Requires-Dist: apache-airflow >= 1.10
Requires-Dist: pyarrow >= 0.13
Requires-Dist: sphinx >= 2.0.0, < 3 ; extra == "docs"
Requires-Dist: sphinx_rtd_theme ; extra == "docs"
Requires-Dist: pyspark >= 2.3 ; extra == "pyspark"
Requires-Dist: pytest-cov ; extra == "testing"
Requires-Dist: pytest ; extra == "testing"
Requires-Dist: xlrd ; extra == "testing"
Requires-Dist: flake8 ; extra == "testing"
Requires-Dist: xlwt ; extra == "testing"
Project-URL: Documentation, https://joerg-schneider.github.io/airtunnel/
Project-URL: Repository, https://github.com/joerg-schneider/airtunnel
Provides-Extra: docs
Provides-Extra: pyspark
Provides-Extra: testing
